feature_extractor/__init__.py
feature_extractor/feature_config.py
feature_extractor/feature_extractor.py
feature_extractor/ex_proto/__init__.py
feature_extractor/ex_proto/rank_pb2.py
feature_extractor/lib/__init__.py
feature_extractor/lib/method_list.py
feature_extractor/utils/__init__.py
feature_extractor/utils/json2prototxt.py
feature_extractor/utils/pbjson.py
feature_extractor/utils/schema_parse.py
acg_feature_extractor-0.0.2.dist-info/METADATA
acg_feature_extractor-0.0.2.dist-info/WHEEL
acg_feature_extractor-0.0.2.dist-info/top_level.txt
acg_feature_extractor-0.0.2.dist-info/RECORD
