Metadata-Version: 2.1
Name: acg-feature-extractor
Version: 0.0.2
Summary: General feature extractor
Home-page: http://icode.baidu.com/repos/baidu/acg-imt/feature-extractor-lite/tree/master
Author: dongdaxiang
Author-email: dongdaxiang@baidu.com
License: Apache 2.0
Platform: UNKNOWN
Classifier: Development Status :: 4 - Beta
Classifier: Intended Audience :: Developers
Classifier: Intended Audience :: Education
Classifier: Intended Audience :: Science/Research
Classifier: License :: OSI Approved :: Apache Software License
Classifier: Programming Language :: Python :: 2
Classifier: Programming Language :: Python :: 3
Classifier: Topic :: Scientific/Engineering
Classifier: Topic :: Scientific/Engineering :: Mathematics
Classifier: Topic :: Scientific/Engineering :: Artificial Intelligence
Classifier: Topic :: Software Development
Classifier: Topic :: Software Development :: Libraries
Classifier: Topic :: Software Development :: Libraries :: Python Modules
Requires-Dist: protobuf (==3.13.0)
Requires-Dist: ujson (==2.0.3)
Requires-Dist: grpcio-tools (==1.32.0)
Requires-Dist: xxhash (==2.0.0)
